django_lazy_tags-0.5.0.dist-info/DESCRIPTION.rst
django_lazy_tags-0.5.0.dist-info/METADATA
django_lazy_tags-0.5.0.dist-info/RECORD
django_lazy_tags-0.5.0.dist-info/WHEEL
django_lazy_tags-0.5.0.dist-info/metadata.json
django_lazy_tags-0.5.0.dist-info/top_level.txt
lazy_tags/__init__.py
lazy_tags/decorators.py
lazy_tags/urls.py
lazy_tags/utils.py
lazy_tags/views.py
lazy_tags/static/img/lazy_tags/spinner.gif
lazy_tags/templates/lazy_tags/lazy_tag.html
lazy_tags/templates/lazy_tags/lazy_tags_javascript.html
lazy_tags/templates/lazy_tags/lazy_tags_jquery.html
lazy_tags/templates/lazy_tags/lazy_tags_prototype.html
lazy_tags/templatetags/__init__.py
lazy_tags/templatetags/lazy_tags.py
tests/templatetags/__init__.py
tests/templatetags/test_tags.py
tests/templatetags/tests/__init__.py
tests/templatetags/tests/nested_tags.py
