Metadata-Version: 2.0
Name: django-lazy-tags
Version: 0.5.0
Summary: A Django app for lazy loading template tags over AJAX
Home-page: https://github.com/grantmcconnaughey/django-lazy-tags/
Author: Grant McConnaughey
Author-email: grantmcconnaughey@gmail.com
License: MIT
Keywords: ajax,django,templatetag
Platform: UNKNOWN
Classifier: Development Status :: 4 - Beta
Classifier: Environment :: Web Environment
Classifier: Framework :: Django
Classifier: Framework :: Django :: 1.9
Classifier: Framework :: Django :: 1.10
Classifier: Framework :: Django :: 1.11
Classifier: Framework :: Django :: 2.0
Classifier: Intended Audience :: Developers
Classifier: License :: OSI Approved :: MIT License
Classifier: Operating System :: OS Independent
Classifier: Programming Language :: Python
Classifier: Programming Language :: Python :: 2.7
Classifier: Programming Language :: Python :: 3.4
Classifier: Programming Language :: Python :: 3.5
Classifier: Programming Language :: Python :: 3.6
